{"name":"build-javascript","namedChunkGroups":{"app":{"name":"app","assets":[{"name":"webpack-runtime-6cc00938cbb8719ca01b.js","size":3877},{"name":"framework-26463179e9787161df51.js","size":141393},{"name":"app-032289b4f0acce41628f.js","size":86816}],"filteredAssets":0,"assetsSize":232086,"filteredAuxiliaryAssets":3,"auxiliaryAssetsSize":737142},"component---src-pages-404-jsx":{"name":"component---src-pages-404-jsx","assets":[{"name":"component---src-pages-404-jsx-e25d7f5ae76faa1a060d.js","size":503}],"filteredAssets":0,"assetsSize":503,"filteredAuxiliaryAssets":1,"auxiliaryAssetsSize":1067},"component---src-pages-index-jsx":{"name":"component---src-pages-index-jsx","assets":[{"name":"framework-26463179e9787161df51.js","size":141393},{"name":"feda10ed335760d506ec0025cf5c1f2ab0711817-a41712e400cce3b35e1b.js","size":24850},{"name":"component---src-pages-index-jsx-6a1111324032328ce5d7.js","size":3894}],"filteredAssets":0,"assetsSize":170137,"filteredAuxiliaryAssets":3,"auxiliaryAssetsSize":496323},"component---src-pages-play-jsx":{"name":"component---src-pages-play-jsx","assets":[{"name":"framework-26463179e9787161df51.js","size":141393},{"name":"7112840a-78f439a90988a15ff477.js","size":163343},{"name":"feda10ed335760d506ec0025cf5c1f2ab0711817-a41712e400cce3b35e1b.js","size":24850},{"name":"component---src-pages-play-jsx-70cec2af1714141c4198.js","size":83021}],"filteredAssets":0,"assetsSize":412607,"filteredAuxiliaryAssets":4,"auxiliaryAssetsSize":2042152}},"assetsByChunkName":{"app":["webpack-runtime-6cc00938cbb8719ca01b.js","framework-26463179e9787161df51.js","app-032289b4f0acce41628f.js"],"component---src-pages-404-jsx":["component---src-pages-404-jsx-e25d7f5ae76faa1a060d.js"],"component---src-pages-index-jsx":["framework-26463179e9787161df51.js","feda10ed335760d506ec0025cf5c1f2ab0711817-a41712e400cce3b35e1b.js","component---src-pages-index-jsx-6a1111324032328ce5d7.js"],"component---src-pages-play-jsx":["framework-26463179e9787161df51.js","7112840a-78f439a90988a15ff477.js","feda10ed335760d506ec0025cf5c1f2ab0711817-a41712e400cce3b35e1b.js","component---src-pages-play-jsx-70cec2af1714141c4198.js"]},"childAssetsByChunkName":{}}